{"version":1,"resource":"vscode-remote://970-cs-6f192dbb-5731-46ba-a29c-f49712529965.cs-us-east1-rtep.cloudshell.dev/home/perrymckay1/myPostedLoads.js","entries":[{"id":"pwuA.js","source":"Workspace Edit","timestamp":1774311736515},{"id":"gJNN.js","source":"Workspace Edit","timestamp":1774311891867},{"id":"00w2.js","source":"Workspace Edit","timestamp":1774312065764},{"id":"Vhjo.js","source":"Workspace Edit","timestamp":1774312350445},{"id":"nKnw.js","source":"Workspace Edit","timestamp":1774312611374},{"id":"UIbU.js","source":"Workspace Edit","timestamp":1774316374266},{"id":"VAOr.js","source":"Workspace Edit","timestamp":1774316397852}]}